yaz_pyutils/__init__.py
yaz_pyutils/py.typed
yaz_pyutils/randoms/__init__.py
yaz_pyutils/randoms/generate.py
yaz_pyutils-0.0.1.dist-info/METADATA
yaz_pyutils-0.0.1.dist-info/WHEEL
yaz_pyutils-0.0.1.dist-info/licenses/LICENSE
yaz_pyutils-0.0.1.dist-info/RECORD
